memtool
