Metadata-Version: 2.4
Name: memtool
Version: 0.1.1
Summary: Memory management and manual allocation library for Python using C
Home-page: https://github.com/s7n5c4n/memtool
Author: S7n5c4n
Author-email: cr.hachim2.0@egmail.com
License: MIT
Classifier: Programming Language :: Python :: 3
Classifier: Programming Language :: C
Classifier: Operating System :: OS Independent
Classifier: License :: OSI Approved :: MIT License
Classifier: Topic :: Software Development :: Libraries :: Python Modules
Requires-Python: >=3.7
Dynamic: author
Dynamic: author-email
Dynamic: classifier
Dynamic: description
Dynamic: description-content-type
Dynamic: home-page
Dynamic: license
Dynamic: requires-python
Dynamic: summary
